{
  "classname": null,
  "name": null,
  "animation": {
    "classname": null,
    "name": "AnimationManager",
    "actionlist": []
  },
  "dataScale": 1,
  "designHeight": 720,
  "designWidth": 1280,
  "textures": [
    "imgRes/popup/popup.plist",
    "imgRes/popup/popup_input.plist",
    "imgRes/common/common_button1.plist"
  ],
  "texturesPng": [
    "imgRes/popup/popup.plist",
    "imgRes/popup/popup_input.plist",
    "imgRes/common/common_button1.plist"
  ],
  "version": "1.6.0.0",
  "widgetTree": {
    "classname": "Panel",
    "name": null,
    "children": [
      {
        "classname": "ImageView",
        "name": null,
        "children": [
          {
            "classname": "ImageView",
            "name": null,
            "children": [],
            "options": {
              "__type": "ImageViewSurrogate:#EditorCommon.JsonModel.Component.GUI",
              "classname": "ImageView",
              "name": "Image_36",
              "ZOrder": 0,
              "actiontag": 26882864,
              "anchorPointX": 0.5,
              "anchorPointY": 0.5,
              "classType": "CocoStudio.EngineAdapterWrap.CSImageView",
              "colorB": 255,
              "colorG": 255,
              "colorR": 255,
              "customProperty": "",
              "flipX": false,
              "flipY": false,
              "height": 80,
              "ignoreSize": false,
              "layoutParameter": null,
              "opacity": 255,
              "positionPercentX": 0,
              "positionPercentY": 0.385,
              "positionType": 0,
              "rotation": 0,
              "scaleX": 1,
              "scaleY": 1,
              "sizePercentX": 0.5243243,
              "sizePercentY": 0.2,
              "sizeType": 0,
              "tag": 1000674051,
              "touchAble": false,
              "useMergedTexture": false,
              "visible": true,
              "width": 388,
              "x": 0,
              "y": 154,
              "capInsetsHeight": 1,
              "capInsetsWidth": 1,
              "capInsetsX": 100,
              "capInsetsY": 0,
              "fileName": null,
              "fileNameData": {
                "path": "popup_titlebg1.png",
                "plistFile": "imgRes/popup/popup.plist",
                "resourceType": 1
              },
              "scale9Enable": true,
              "scale9Height": 80,
              "scale9Width": 388
            }
          },
          {
            "classname": "Label",
            "name": null,
            "children": [],
            "options": {
              "__type": "LabelSurrogate:#EditorCommon.JsonModel.Component.GUI",
              "classname": "Label",
              "name": "Label_title",
              "ZOrder": 0,
              "actiontag": 57039221,
              "anchorPointX": 0.5,
              "anchorPointY": 0.5,
              "classType": "CocoStudio.EngineAdapterWrap.CSLabel",
              "colorB": 224,
              "colorG": 248,
              "colorR": 253,
              "customProperty": "",
              "flipX": false,
              "flipY": false,
              "height": 42,
              "ignoreSize": true,
              "layoutParameter": null,
              "opacity": 255,
              "positionPercentX": 0,
              "positionPercentY": 0.39,
              "positionType": 0,
              "rotation": 0,
              "scaleX": 1,
              "scaleY": 1,
              "sizePercentX": 0.2837838,
              "sizePercentY": 0.105,
              "sizeType": 0,
              "tag": 1000674052,
              "touchAble": false,
              "useMergedTexture": false,
              "visible": true,
              "width": 210,
              "x": 0,
              "y": 156,
              "areaHeight": 0,
              "areaWidth": 0,
              "fontFile": null,
              "fontName": "font/font_res_at1.ttf",
              "fontSize": 42,
              "hAlignment": 0,
              "text": "绑定邀请码",
              "touchScaleEnable": false,
              "vAlignment": 0
            }
          },
          {
            "classname": "Button",
            "name": null,
            "children": [],
            "options": {
              "__type": "ButtonSurrogate:#EditorCommon.JsonModel.Component.GUI",
              "classname": "Button",
              "name": "close_btn",
              "ZOrder": 0,
              "actiontag": 65453921,
              "anchorPointX": 0.5,
              "anchorPointY": 0.5,
              "classType": "CocoStudio.EngineAdapterWrap.CSButton",
              "colorB": 255,
              "colorG": 255,
              "colorR": 255,
              "customProperty": "",
              "flipX": false,
              "flipY": false,
              "height": 77,
              "ignoreSize": true,
              "layoutParameter": null,
              "opacity": 255,
              "positionPercentX": 0.432432443,
              "positionPercentY": 0.3775,
              "positionType": 0,
              "rotation": 0,
              "scaleX": 1,
              "scaleY": 1,
              "sizePercentX": 0.1527027,
              "sizePercentY": 0.2575,
              "sizeType": 0,
              "tag": 1000519875,
              "touchAble": true,
              "useMergedTexture": false,
              "visible": true,
              "width": 77,
              "x": 320,
              "y": 151,
              "capInsetsHeight": 1,
              "capInsetsWidth": 1,
              "capInsetsX": 0,
              "capInsetsY": 0,
              "disabled": null,
              "disabledData": {
                "path": null,
                "plistFile": null,
                "resourceType": 0
              },
              "fontName": "微软雅黑",
              "fontSize": 14,
              "fontType": 0,
              "normal": null,
              "normalData": {
                "path": "popup_btn_close.png",
                "plistFile": "imgRes/popup/popup.plist",
                "resourceType": 1
              },
              "pressed": null,
              "pressedData": {
                "path": null,
                "plistFile": null,
                "resourceType": 0
              },
              "scale9Enable": false,
              "scale9Height": 77,
              "scale9Width": 77,
              "text": "",
              "textColorB": 255,
              "textColorG": 255,
              "textColorR": 255
            }
          },
          {
            "classname": "Label",
            "name": null,
            "children": [],
            "options": {
              "__type": "LabelSurrogate:#EditorCommon.JsonModel.Component.GUI",
              "classname": "Label",
              "name": "Label_4",
              "ZOrder": 0,
              "actiontag": 27033300,
              "anchorPointX": 0.5,
              "anchorPointY": 0.5,
              "classType": "CocoStudio.EngineAdapterWrap.CSLabel",
              "colorB": 74,
              "colorG": 81,
              "colorR": 115,
              "customProperty": "",
              "flipX": false,
              "flipY": false,
              "height": 36,
              "ignoreSize": true,
              "layoutParameter": null,
              "opacity": 255,
              "positionPercentX": -0.229729727,
              "positionPercentY": 0.05,
              "positionType": 0,
              "rotation": 0,
              "scaleX": 1,
              "scaleY": 1,
              "sizePercentX": 0.194594592,
              "sizePercentY": 0.09,
              "sizeType": 0,
              "tag": 1000519876,
              "touchAble": false,
              "useMergedTexture": false,
              "visible": true,
              "width": 144,
              "x": -170,
              "y": 20,
              "areaHeight": 0,
              "areaWidth": 0,
              "fontFile": null,
              "fontName": "font/font_res_at2.ttf",
              "fontSize": 36,
              "hAlignment": 0,
              "text": "邀请码：",
              "touchScaleEnable": false,
              "vAlignment": 0
            }
          },
          {
            "classname": "ImageView",
            "name": null,
            "children": [],
            "options": {
              "__type": "ImageViewSurrogate:#EditorCommon.JsonModel.Component.GUI",
              "classname": "ImageView",
              "name": "input_bg",
              "ZOrder": 0,
              "actiontag": 48938121,
              "anchorPointX": 0.5,
              "anchorPointY": 0.5,
              "classType": "CocoStudio.EngineAdapterWrap.CSImageView",
              "colorB": 255,
              "colorG": 255,
              "colorR": 255,
              "customProperty": "",
              "flipX": false,
              "flipY": false,
              "height": 70,
              "ignoreSize": false,
              "layoutParameter": null,
              "opacity": 255,
              "positionPercentX": 0.09054054,
              "positionPercentY": 0.05,
              "positionType": 0,
              "rotation": 0,
              "scaleX": 1,
              "scaleY": 1,
              "sizePercentX": 0.445945948,
              "sizePercentY": 0.175,
              "sizeType": 0,
              "tag": 1000519877,
              "touchAble": false,
              "useMergedTexture": false,
              "visible": true,
              "width": 330,
              "x": 67,
              "y": 20,
              "capInsetsHeight": 1,
              "capInsetsWidth": 1,
              "capInsetsX": 125,
              "capInsetsY": 23,
              "fileName": null,
              "fileNameData": {
                "path": "popup_input_inputBg5.png",
                "plistFile": "imgRes/popup/popup_input.plist",
                "resourceType": 1
              },
              "scale9Enable": true,
              "scale9Height": 70,
              "scale9Width": 330
            }
          },
          {
            "classname": "Button",
            "name": null,
            "children": [],
            "options": {
              "__type": "ButtonSurrogate:#EditorCommon.JsonModel.Component.GUI",
              "classname": "Button",
              "name": "btn_bind",
              "ZOrder": 0,
              "actiontag": 60042939,
              "anchorPointX": 0.5,
              "anchorPointY": 0.5,
              "classType": "CocoStudio.EngineAdapterWrap.CSButton",
              "colorB": 255,
              "colorG": 255,
              "colorR": 255,
              "customProperty": "",
              "flipX": false,
              "flipY": false,
              "height": 82,
              "ignoreSize": true,
              "layoutParameter": null,
              "opacity": 255,
              "positionPercentX": 0,
              "positionPercentY": -0.2625,
              "positionType": 0,
              "rotation": 0,
              "scaleX": 1,
              "scaleY": 1,
              "sizePercentX": 0.2837838,
              "sizePercentY": 0.205,
              "sizeType": 0,
              "tag": 1000519878,
              "touchAble": true,
              "useMergedTexture": false,
              "visible": true,
              "width": 210,
              "x": 0,
              "y": -105,
              "capInsetsHeight": 1,
              "capInsetsWidth": 1,
              "capInsetsX": 0,
              "capInsetsY": 0,
              "disabled": null,
              "disabledData": {
                "path": null,
                "plistFile": null,
                "resourceType": 0
              },
              "fontName": "微软雅黑",
              "fontSize": 14,
              "fontType": 0,
              "normal": null,
              "normalData": {
                "path": "common_btn_quedingbanding.png",
                "plistFile": "imgRes/common/common_button1.plist",
                "resourceType": 1
              },
              "pressed": null,
              "pressedData": {
                "path": null,
                "plistFile": null,
                "resourceType": 0
              },
              "scale9Enable": false,
              "scale9Height": 82,
              "scale9Width": 210,
              "text": "",
              "textColorB": 255,
              "textColorG": 255,
              "textColorR": 255
            }
          }
        ],
        "options": {
          "__type": "ImageViewSurrogate:#EditorCommon.JsonModel.Component.GUI",
          "classname": "ImageView",
          "name": "layerBg",
          "ZOrder": 0,
          "actiontag": 5601312,
          "anchorPointX": 0.5,
          "anchorPointY": 0.5,
          "classType": "CocoStudio.EngineAdapterWrap.CSImageView",
          "colorB": 255,
          "colorG": 255,
          "colorR": 255,
          "customProperty": "",
          "flipX": false,
          "flipY": false,
          "height": 400,
          "ignoreSize": false,
          "layoutParameter": null,
          "opacity": 255,
          "positionPercentX": 0.5,
          "positionPercentY": 0.5,
          "positionType": 0,
          "rotation": 0,
          "scaleX": 1,
          "scaleY": 1,
          "sizePercentX": 0.578125,
          "sizePercentY": 0.5555556,
          "sizeType": 0,
          "tag": 1000519873,
          "touchAble": false,
          "useMergedTexture": false,
          "visible": true,
          "width": 740,
          "x": 640,
          "y": 360,
          "capInsetsHeight": 1,
          "capInsetsWidth": 1,
          "capInsetsX": 40,
          "capInsetsY": 30,
          "fileName": null,
          "fileNameData": {
            "path": "popup_bg0.png",
            "plistFile": "imgRes/popup/popup.plist",
            "resourceType": 1
          },
          "scale9Enable": true,
          "scale9Height": 400,
          "scale9Width": 740
        }
      }
    ],
    "options": {
      "__type": "PanelSurrogate:#EditorCommon.JsonModel.Component.GUI",
      "classname": "Panel",
      "name": "mianPopup",
      "ZOrder": 0,
      "actiontag": -1,
      "anchorPointX": 0,
      "anchorPointY": 0,
      "classType": "CocoStudio.EngineAdapterWrap.CSPanel",
      "colorB": 255,
      "colorG": 255,
      "colorR": 255,
      "customProperty": "",
      "flipX": false,
      "flipY": false,
      "height": 720,
      "ignoreSize": false,
      "layoutParameter": null,
      "opacity": 255,
      "positionPercentX": 0,
      "positionPercentY": 0,
      "positionType": 0,
      "rotation": 0,
      "scaleX": 1,
      "scaleY": 1,
      "sizePercentX": 1,
      "sizePercentY": 1,
      "sizeType": 0,
      "tag": 1000671776,
      "touchAble": true,
      "useMergedTexture": false,
      "visible": true,
      "width": 1280,
      "x": 0,
      "y": 0,
      "adaptScreen": false,
      "backGroundImage": null,
      "backGroundImageData": null,
      "backGroundScale9Enable": false,
      "bgColorB": 255,
      "bgColorG": 200,
      "bgColorOpacity": 0,
      "bgColorR": 150,
      "bgEndColorB": 255,
      "bgEndColorG": 200,
      "bgEndColorR": 150,
      "bgStartColorB": 255,
      "bgStartColorG": 255,
      "bgStartColorR": 255,
      "capInsetsHeight": 1,
      "capInsetsWidth": 1,
      "capInsetsX": 0,
      "capInsetsY": 0,
      "clipAble": false,
      "colorType": 0,
      "layoutType": 0,
      "vectorX": 0,
      "vectorY": -0.5
    }
  }
}